{
    "created_time": "2024-05-06T01:12:12Z",
    "files": [
        {
            "attachment_folder": "",
            "created_time": "2024-05-06T01:12:12Z",
            "id": "14294",
            "modified_time": "2024-05-06T01:12:12Z",
            "name": "_sidebar.md",
            "signature": "16111827045309754988",
            "tags": [
            ]
        },
        {
            "attachment_folder": "",
            "created_time": "2024-05-06T01:12:13Z",
            "id": "14300",
            "modified_time": "2024-05-06T01:12:13Z",
            "name": "K8s API Server未授权命令执行.md",
            "signature": "15272547473113493101",
            "tags": [
            ]
        },
        {
            "attachment_folder": "",
            "created_time": "2024-05-06T01:12:13Z",
            "id": "14303",
            "modified_time": "2024-05-06T01:12:13Z",
            "name": "K8s-API-Server未授权命令执行.md",
            "signature": "2966807103046954605",
            "tags": [
            ]
        },
        {
            "attachment_folder": "",
            "created_time": "2024-05-06T01:12:13Z",
            "id": "14306",
            "modified_time": "2024-05-06T01:12:13Z",
            "name": "README.md",
            "signature": "5261922976172355181",
            "tags": [
            ]
        }
    ],
    "folders": [
        {
            "name": "images"
        }
    ],
    "id": "14305",
    "modified_time": "2024-05-06T01:12:12Z",
    "signature": "12499342984790683244",
    "version": 3
}
