{
    "created_time": "2024-05-06T01:09:35Z",
    "files": [
    ],
    "folders": [
        {
            "name": "Emlog 6.0 xss集合"
        },
        {
            "name": "Emlog 6.0 后台暴力破解"
        },
        {
            "name": "Emlog 6.0 数据库备份与导入功能导致后台getshell"
        },
        {
            "name": "Emlog phpinfo 泄漏"
        },
        {
            "name": "Emlog 友情链接自助插件存在SQL注入漏洞"
        },
        {
            "name": "Emlog 相册插件前台SQL注入+Getshell"
        },
        {
            "name": "Emlog 越权&后台getshell"
        }
    ],
    "id": "3897",
    "modified_time": "2024-05-06T01:09:35Z",
    "signature": "8359764611967757775",
    "version": 3
}
