{
    "created_time": "2024-05-06T01:10:52Z",
    "files": [
        {
            "attachment_folder": "",
            "created_time": "2024-05-06T01:10:52Z",
            "id": "9010",
            "modified_time": "2024-05-06T01:10:52Z",
            "name": "ThinkCMF任意内容包含漏洞getshell.md",
            "signature": "15006957763659574812",
            "tags": [
            ]
        }
    ],
    "folders": [
        {
            "name": "resource"
        }
    ],
    "id": "9007",
    "modified_time": "2024-05-06T01:10:52Z",
    "signature": "5357168596130213404",
    "version": 3
}
