{
    "created_time": "2024-05-06T01:11:18Z",
    "files": [
        {
            "attachment_folder": "",
            "created_time": "2024-05-06T01:11:18Z",
            "id": "10748",
            "modified_time": "2024-05-06T01:11:18Z",
            "name": "WordPress Plugin - NextGEN Gallery = 3.2.2 RCE .md",
            "signature": "10517866930951958070",
            "tags": [
            ]
        }
    ],
    "folders": [
        {
            "name": "resource"
        }
    ],
    "id": "10739",
    "modified_time": "2024-05-06T01:11:18Z",
    "signature": "11259368454508523062",
    "version": 3
}
