{
    "created_time": "2024-05-06T01:10:30Z",
    "files": [
        {
            "attachment_folder": "",
            "created_time": "2024-05-06T01:10:30Z",
            "id": "7501",
            "modified_time": "2024-05-06T01:10:30Z",
            "name": "Phpcms V9.6.3 前台getshell.md",
            "signature": "16484211481650933254",
            "tags": [
            ]
        }
    ],
    "folders": [
    ],
    "id": "7500",
    "modified_time": "2024-05-06T01:10:30Z",
    "signature": "4984689975451201030",
    "version": 3
}
