{
    "created_time": "2024-05-06T01:11:28Z",
    "files": [
        {
            "attachment_folder": "",
            "created_time": "2024-05-06T01:11:28Z",
            "id": "11275",
            "modified_time": "2024-05-06T01:11:28Z",
            "name": "XYHCMS 3.6 后台代码执行漏洞（二）.md",
            "signature": "16386688850421362240",
            "tags": [
            ]
        }
    ],
    "folders": [
    ],
    "id": "11274",
    "modified_time": "2024-05-06T01:11:28Z",
    "signature": "3534937139214560832",
    "version": 3
}
